MANIFEST.in
setup.py
zweb/__init__.py
zweb/_import.py
zweb/app_install.py
zweb/attrcache.py
zweb/config_loader.py
zweb/errtip.py
zweb/print_route.py
zweb/route.py
zweb/script.py
zweb/sentry.py
zweb/signal.py
zweb.egg-info/PKG-INFO
zweb.egg-info/SOURCES.txt
zweb.egg-info/dependency_links.txt
zweb.egg-info/entry_points.txt
zweb.egg-info/not-zip-safe
zweb.egg-info/requires.txt
zweb.egg-info/top_level.txt
zweb/lib/__init__.py
zweb/lib/jsdict.py
zweb/lib/single_process.py
zweb/lib/tld_name.py
zweb/lib/mako/__init__.py
zweb/lib/mako/_ast_util.py
zweb/lib/mako/ast.py
zweb/lib/mako/cache.py
zweb/lib/mako/codegen.py
zweb/lib/mako/exceptions.py
zweb/lib/mako/filters.py
zweb/lib/mako/lexer.py
zweb/lib/mako/lookup.py
zweb/lib/mako/parsetree.py
zweb/lib/mako/pygen.py
zweb/lib/mako/pyparser.py
zweb/lib/mako/runtime.py
zweb/lib/mako/template.py
zweb/lib/mako/util.py
zweb/lib/mako/ext/__init__.py
zweb/lib/mako/ext/autohandler.py
zweb/lib/mako/ext/babelplugin.py
zweb/lib/mako/ext/beaker_cache.py
zweb/lib/mako/ext/preprocessors.py
zweb/lib/mako/ext/pygmentplugin.py
zweb/lib/mako/ext/turbogears.py
zweb/reloader/__init__.py
zweb/reloader/reload_server.py
zweb/reloader/reloader.py
zweb/server/__init__.py
zweb/server/_tornado.py
zweb/server/_webob_fix.py
zweb/server/errormiddleware.py
zweb/server/profile_middleware.py
zweb/server/server_cherry.py
zweb/server/server_tornado.py
zweb/server/server_tornado_wsgi.py
zweb/server/tornado_graceful_stop.py
zweb/template/__init__.py
zweb/template/app.tgz
zweb/template/project.tgz
zweb/template/app/__init__.py
zweb/template/app/coffee/__init__.py
zweb/template/app/css/__init__.py
zweb/template/app/css/_img/__init__.py
zweb/template/app/html/__init__.py
zweb/template/app/html/root/index.html
zweb/template/app/js/__init__.py
zweb/template/app/misc/__init__.py
zweb/template/app/misc/backup/__init__.py
zweb/template/app/misc/config/__init__.py
zweb/template/app/misc/config/_table.py
zweb/template/app/misc/config/default.py
zweb/template/app/misc/config/_host/__init__.py
zweb/template/app/misc/config/_user/__init__.py
zweb/template/app/misc/crontab/__init__.py
zweb/template/app/misc/file/__init__.py
zweb/template/app/misc/lib/__init__.py
