Metadata-Version: 1.0
Name: zweb
Version: 0.4309
Summary: A web site framework
Home-page: UNKNOWN
Author: zuroc 张沈鹏
Author-email: zsp042@gmail.com
License: UNKNOWN
Platform: UNKNOWN
